ProgramizShujujiegouHeSuanfaJiaochengChuyi/README.md
ProgramizShujujiegouHeSuanfaJiaochengChuyi/__init__.py
ProgramizShujujiegouHeSuanfaJiaochengChuyi/__main__.py
ProgramizShujujiegouHeSuanfaJiaochengChuyi/file.epub
ProgramizShujujiegouHeSuanfaJiaochengChuyi/index.html
ProgramizShujujiegouHeSuanfaJiaochengChuyi/css/__init__.py
ProgramizShujujiegouHeSuanfaJiaochengChuyi/css/annotations.css
ProgramizShujujiegouHeSuanfaJiaochengChuyi/css/main.css
ProgramizShujujiegouHeSuanfaJiaochengChuyi/css/normalize.css
ProgramizShujujiegouHeSuanfaJiaochengChuyi/css/popup.css
ProgramizShujujiegouHeSuanfaJiaochengChuyi/font/__init__.py
ProgramizShujujiegouHeSuanfaJiaochengChuyi/font/fontello.eot
ProgramizShujujiegouHeSuanfaJiaochengChuyi/font/fontello.svg
ProgramizShujujiegouHeSuanfaJiaochengChuyi/font/fontello.ttf
ProgramizShujujiegouHeSuanfaJiaochengChuyi/font/fontello.woff
ProgramizShujujiegouHeSuanfaJiaochengChuyi/img/__init__.py
ProgramizShujujiegouHeSuanfaJiaochengChuyi/img/annotator-glyph-sprite.png
ProgramizShujujiegouHeSuanfaJiaochengChuyi/img/annotator-icon-sprite.png
ProgramizShujujiegouHeSuanfaJiaochengChuyi/img/apple-touch-icon.png
ProgramizShujujiegouHeSuanfaJiaochengChuyi/img/cancelfullscreen.png
ProgramizShujujiegouHeSuanfaJiaochengChuyi/img/close.png
ProgramizShujujiegouHeSuanfaJiaochengChuyi/img/fullscreen.png
ProgramizShujujiegouHeSuanfaJiaochengChuyi/img/loader.gif
ProgramizShujujiegouHeSuanfaJiaochengChuyi/img/menu-icon.png
ProgramizShujujiegouHeSuanfaJiaochengChuyi/img/save.png
ProgramizShujujiegouHeSuanfaJiaochengChuyi/img/saved.png
ProgramizShujujiegouHeSuanfaJiaochengChuyi/img/settings-s.png
ProgramizShujujiegouHeSuanfaJiaochengChuyi/img/settings.png
ProgramizShujujiegouHeSuanfaJiaochengChuyi/img/star.png
ProgramizShujujiegouHeSuanfaJiaochengChuyi/js/__init__.py
ProgramizShujujiegouHeSuanfaJiaochengChuyi/js/epub.js
ProgramizShujujiegouHeSuanfaJiaochengChuyi/js/epub.min.js
ProgramizShujujiegouHeSuanfaJiaochengChuyi/js/epub.min.map
programiz_shujujiegou_he_suanfa_jiaocheng_chuyi-2024.3.5.0.dist-info/METADATA
programiz_shujujiegou_he_suanfa_jiaocheng_chuyi-2024.3.5.0.dist-info/WHEEL
programiz_shujujiegou_he_suanfa_jiaocheng_chuyi-2024.3.5.0.dist-info/entry_points.txt
programiz_shujujiegou_he_suanfa_jiaocheng_chuyi-2024.3.5.0.dist-info/top_level.txt
programiz_shujujiegou_he_suanfa_jiaocheng_chuyi-2024.3.5.0.dist-info/RECORD
